configg/__init__.py
configg/backend.py
configg/configg.py
configg/exceptions.py
configg/ini_backend.py
configg/json_backend.py
configg/section_view.py
configg/xml_backend.py
configg-0.6a0.dist-info/LICENSE
configg-0.6a0.dist-info/METADATA
configg-0.6a0.dist-info/WHEEL
configg-0.6a0.dist-info/top_level.txt
configg-0.6a0.dist-info/RECORD
