Metadata-Version: 2.1
Name: configg
Version: 0.6a0
Summary: Config data manager
Home-page: https://github.com/ok65/Configg
Author: Oliver
Author-email: mail.ok65@googlemail.com
License: UNKNOWN
Platform: UNKNOWN
